searchpubmed/__init__.py
searchpubmed/pubmed.py
searchpubmed/query_builder.py
searchpubmed-0.5.3.dist-info/licenses/LICENSE
searchpubmed-0.5.3.dist-info/METADATA
searchpubmed-0.5.3.dist-info/WHEEL
searchpubmed-0.5.3.dist-info/top_level.txt
searchpubmed-0.5.3.dist-info/RECORD
