Metadata-Version: 2.4
Name: searchpubmed
Version: 0.5.3
Summary: High-level helpers for PubMed search, metadata & full-text retrieval.
Author-email: Gowtham Rao <rao@ohdsi.org>
Maintainer-email: Gowtham Rao <rao@ohdsi.org>
License:                                  Apache License
Project-URL: Homepage, https://github.com/OHDSI/SearchPubmed
Project-URL: Changelog, https://github.com/OHDSI/SearchPubmed/releases
Project-URL: Documentation, https://github.com/OHDSI/SearchPubmed/wiki
Keywords: PubMed,OHDSI,Epidemiology,Literature
Classifier: Development Status :: 4 - Beta
Classifier: License :: OSI Approved :: Apache Software License
Classifier: Programming Language :: Python :: 3.9
Classifier: Programming Language :: Python :: 3.10
Classifier: Programming Language :: Python :: 3.11
Classifier: Programming Language :: Python :: 3.12
Classifier: Topic :: Scientific/Engineering :: Information Analysis
Requires-Python: >=3.9
License-File: LICENSE
Requires-Dist: requests>=2.31
Requires-Dist: pandas>=1.5
Requires-Dist: beautifulsoup4>=4.12
Requires-Dist: dateparser>=1.1
Provides-Extra: dev
Requires-Dist: pytest>=7; extra == "dev"
Requires-Dist: pytest-cov>=6; extra == "dev"
Requires-Dist: requests-mock>=1.11; extra == "dev"
Requires-Dist: flake8>=6; extra == "dev"
Requires-Dist: black>=24; extra == "dev"
Requires-Dist: mypy>=1.9; extra == "dev"
Requires-Dist: isort>=5.13; extra == "dev"
Dynamic: license-file
